<?xml version="1.0" encoding="UTF-8"?>
<exercicio
 xmlns="exercicio"
 xmlns:xsi="exercicio"
 xsi:schemaLocation="/src/dominio/exercicio.xsd">

		<disciplina>INF41</disciplina>
		<conteudo>vetor</conteudo>	
		<idEx>v004</idEx>
		<nivel>facil</nivel>
		<tipo>me</tipo>
		<preReq>
			<req></req>
		</preReq>

		<enunciado> 
			<texto>Os vetores são matrizes de quantas dimensões:</texto> 
		</enunciado>
		
		<resposta> </resposta>

		<alternativa valor="true"> 
			<texto>1 dimensão</texto>
		</alternativa>
		
		<alternativa valor="false"> 
			<texto>0 dimensão</texto>	
		</alternativa>
		
		<alternativa valor="false"> 
			<texto>2 dimensões</texto>
		</alternativa>
		
		<alternativa valor="false"> 
			<texto>Nenhuma das anteriores.</texto>
		</alternativa>

</exercicio>

